tor_file_parsers/__init__.py
tor_file_parsers/line2kv.py
tor_file_parsers/parse_real_v3bw.py
tor_file_parsers/parse_tornettools_v3bw.py
tor_file_parsers/v3bw.py
tor_file_parsers-0.1.0.dist-info/LICENSE
tor_file_parsers-0.1.0.dist-info/METADATA
tor_file_parsers-0.1.0.dist-info/WHEEL
tor_file_parsers-0.1.0.dist-info/top_level.txt
tor_file_parsers-0.1.0.dist-info/RECORD
